ratelimit_io/__init__.py
ratelimit_io/rate_limit.py
ratelimit_io-0.6.5.dist-info/LICENSE
ratelimit_io-0.6.5.dist-info/METADATA
ratelimit_io-0.6.5.dist-info/WHEEL
ratelimit_io-0.6.5.dist-info/RECORD
