Metadata-Version: 2.1
Name: ratelimit-io
Version: 0.6.5
Summary: Flexible bidirectional rate-limiting library with redis backend
Home-page: https://github.com/bagowix/ratelimit-io
License: MIT
Keywords: rate-limit,ratelimit,rate limit,throttle,rate control,rate-limiting,ratelimiting,limit,limiting,asyncio,I/O,redis,aioredis
Author: Galushko Bogdan
Author-email: galushko355@gmail.com
Requires-Python: >=3.8,<4.0
Classifier: Intended Audience :: Developers
Classifier: License :: OSI Approved :: MIT License
Classifier: Programming Language :: Python :: 3
Classifier: Programming Language :: Python :: 3.8
Classifier: Programming Language :: Python :: 3.9
Classifier: Programming Language :: Python :: 3.10
Classifier: Programming Language :: Python :: 3.11
Classifier: Programming Language :: Python :: 3.12
Classifier: Programming Language :: Python :: 3.13
Classifier: Topic :: Internet
Classifier: Topic :: Software Development :: Libraries
Classifier: Topic :: System :: Networking
Requires-Dist: redis (>=5.2.1,<6.0.0)
Project-URL: Repository, https://github.com/bagowix/ratelimit-io
